pyxstruct/__main__.py
pyxstruct/hbond_search.py
pyxstruct/structure_search.py
pyxstruct-1.0.1.dist-info/DESCRIPTION.rst
pyxstruct-1.0.1.dist-info/METADATA
pyxstruct-1.0.1.dist-info/RECORD
pyxstruct-1.0.1.dist-info/WHEEL
pyxstruct-1.0.1.dist-info/metadata.json
pyxstruct-1.0.1.dist-info/top_level.txt
