Metadata-Version: 2.0
Name: pyxstruct
Version: 1.0.1
Summary: Scrape Geometric X-ray Data from the Cambridge Structural Database 
Home-page: https://github.com/bobbypaton/pyX-Struct
Author: Paton Research Group
Author-email: robert.paton@colostate.edu
License: UNKNOWN
Download-URL: https://github.com/bobbypaton/pyX-Struct/archive/v1.0.1.zip
Keywords: x-ray structure,CCDC,SMILES,python
Platform: UNKNOWN
Requires-Python: >=2.6
Requires-Dist: numpy
Requires-Dist: seaborn
Requires-Dist: pandas
Requires-Dist: matplotlib
